DemoPkgFrCrunchRoll/CurrentMonth.py
DemoPkgFrCrunchRoll/__init__.py
DemoPkgFrCrunchRoll-0.0.1.dist-info/METADATA
DemoPkgFrCrunchRoll-0.0.1.dist-info/WHEEL
DemoPkgFrCrunchRoll-0.0.1.dist-info/top_level.txt
DemoPkgFrCrunchRoll-0.0.1.dist-info/RECORD
